<?xml version="1.0" encoding="UTF-8" standalone="yes"?>
<boModel>
    <id>33600a65-ffdc-42ff-a89f-a7465e70b525</id>
    <createUser>admin</createUser>
    <createTime>2018-12-27 11:29:32</createTime>
    <updateUser></updateUser>
    <updateTime>2019-05-31 10:16:05</updateTime>
    <signature>tGOmxiTgjT/77UoYpSlq8Vc+hHPRoJWHdZexXc7zEpYuMNdhvSICeJnlc/RzRHGrqNdRrHK7Q/RmAsFtY1iKfoi399uIdUClrn4Lrrd8JwbC3gepqYzGZu7hkgfmYdcm</signature>
    <managed>false</managed>
    <title>附件</title>
    <name>BO_EU_XSHB_FJ</name>
    <collection>false</collection>
    <system>false</system>
    <deleted>false</deleted>
    <categoryName>数据结构</categoryName>
    <administrator>admin</administrator>
    <entityType>TABLE</entityType>
    <viewType></viewType>
    <viewSql></viewSql>
    <securityLevel>0</securityLevel>
    <target>_local</target>
    <itemProps></itemProps>
    <boItems>
        <boItem>
            <id>c116628d-642c-46bf-87ae-4635aa625bb4</id>
            <name>GLYWBH</name>
            <title>关联业务编号</title>
            <columnType>TEXT</columnType>
            <length>30</length>
            <nullable>true</nullable>
            <defaultValue></defaultValue>
            <columnWidth>100</columnWidth>
            <componentId>AWSUI.Text</componentId>
            <componentSetting>{"search":"0"}</componentSetting>
            <display>true</display>
            <deleted>false</deleted>
            <modify>true</modify>
            <componentExtendCode></componentExtendCode>
            <persistenceType>ENTITY</persistenceType>
            <validateType></validateType>
            <validateRule></validateRule>
            <validateTip></validateTip>
            <validateErr>0</validateErr>
            <tooltip></tooltip>
            <copy>false</copy>
            <displayRule></displayRule>
            <calcFormula></calcFormula>
            <propsVal>{}</propsVal>
        </boItem>
        <boItem>
            <id>e1a755eb-f0ae-4d09-8ae4-c374b7c25f50</id>
            <name>FJMC</name>
            <title>附件名称</title>
            <columnType>TEXT</columnType>
            <length>300</length>
            <nullable>true</nullable>
            <defaultValue></defaultValue>
            <columnWidth>200</columnWidth>
            <componentId>AWSUI.Text</componentId>
            <componentSetting>{"search":"0"}</componentSetting>
            <display>true</display>
            <deleted>false</deleted>
            <modify>true</modify>
            <componentExtendCode></componentExtendCode>
            <persistenceType>ENTITY</persistenceType>
            <validateType></validateType>
            <validateRule></validateRule>
            <validateTip></validateTip>
            <validateErr>0</validateErr>
            <tooltip></tooltip>
            <copy>false</copy>
            <displayRule></displayRule>
            <calcFormula></calcFormula>
            <propsVal>{}</propsVal>
        </boItem>
        <boItem>
            <id>f15b0084-9797-41fd-a3cb-925112af9f74</id>
            <name>FJDX</name>
            <title>附件大小</title>
            <columnType>TEXT</columnType>
            <length>10</length>
            <nullable>true</nullable>
            <defaultValue></defaultValue>
            <columnWidth>60</columnWidth>
            <componentId>AWSUI.Text</componentId>
            <componentSetting>{"search":"0"}</componentSetting>
            <display>true</display>
            <deleted>false</deleted>
            <modify>true</modify>
            <componentExtendCode></componentExtendCode>
            <persistenceType>ENTITY</persistenceType>
            <validateType></validateType>
            <validateRule></validateRule>
            <validateTip></validateTip>
            <validateErr>0</validateErr>
            <tooltip></tooltip>
            <copy>false</copy>
            <displayRule></displayRule>
            <calcFormula></calcFormula>
            <propsVal>{}</propsVal>
        </boItem>
        <boItem>
            <id>768fc74c-537c-4790-98ce-166733a58c9e</id>
            <name>FJLX</name>
            <title>附件类型</title>
            <columnType>TEXT</columnType>
            <length>10</length>
            <nullable>true</nullable>
            <defaultValue></defaultValue>
            <columnWidth>60</columnWidth>
            <componentId>AWSUI.Text</componentId>
            <componentSetting>{"search":"0"}</componentSetting>
            <display>true</display>
            <deleted>false</deleted>
            <modify>true</modify>
            <componentExtendCode></componentExtendCode>
            <persistenceType>ENTITY</persistenceType>
            <validateType></validateType>
            <validateRule></validateRule>
            <validateTip></validateTip>
            <validateErr>0</validateErr>
            <tooltip></tooltip>
            <copy>false</copy>
            <displayRule></displayRule>
            <calcFormula></calcFormula>
            <propsVal>{}</propsVal>
        </boItem>
        <boItem>
            <id>70a89a0b-a0e4-4b41-a290-1848ef739c76</id>
            <name>FJLJ</name>
            <title>附件路径</title>
            <columnType>TEXT</columnType>
            <length>300</length>
            <nullable>true</nullable>
            <defaultValue></defaultValue>
            <columnWidth>150</columnWidth>
            <componentId>AWSUI.Text</componentId>
            <componentSetting>{"search":"0"}</componentSetting>
            <display>true</display>
            <deleted>false</deleted>
            <modify>true</modify>
            <componentExtendCode></componentExtendCode>
            <persistenceType>ENTITY</persistenceType>
            <validateType></validateType>
            <validateRule></validateRule>
            <validateTip></validateTip>
            <validateErr>0</validateErr>
            <tooltip></tooltip>
            <copy>false</copy>
            <displayRule></displayRule>
            <calcFormula></calcFormula>
            <propsVal>{}</propsVal>
        </boItem>
        <boItem>
            <id>448bd512-1de5-4cf6-9dac-9a6d6f2011b0</id>
            <name>DJSJ</name>
            <title>登记时间</title>
            <columnType>DATE</columnType>
            <length>0</length>
            <nullable>true</nullable>
            <defaultValue>@datetime</defaultValue>
            <columnWidth>100</columnWidth>
            <componentId>AWSUI.DateTime</componentId>
            <componentSetting>{"placeholder":"","minDate":"","maxDate":"","showtype":"singleCalendar","advSetting":"","dateFmt":"yyyy-MM-dd HH:mm:ss","showDayOfWeek":"false","dwfmt":"(EE)"}</componentSetting>
            <display>true</display>
            <deleted>false</deleted>
            <modify>true</modify>
            <componentExtendCode></componentExtendCode>
            <persistenceType>ENTITY</persistenceType>
            <validateType></validateType>
            <validateRule></validateRule>
            <validateTip></validateTip>
            <validateErr>0</validateErr>
            <tooltip></tooltip>
            <copy>false</copy>
            <displayRule></displayRule>
            <calcFormula></calcFormula>
            <propsVal>{}</propsVal>
        </boItem>
        <boItem>
            <id>f31b3cb1-8c91-4590-ae37-e5b393bb1470</id>
            <name>XXDJDW_GAJGJGDM</name>
            <title>信息登记单位_公安机关机构代码/CODE_GXS</title>
            <columnType>TEXT</columnType>
            <length>12</length>
            <nullable>true</nullable>
            <defaultValue></defaultValue>
            <columnWidth>60</columnWidth>
            <componentId>AWSUI.Text</componentId>
            <componentSetting>{"search":"0"}</componentSetting>
            <display>true</display>
            <deleted>false</deleted>
            <modify>true</modify>
            <componentExtendCode></componentExtendCode>
            <persistenceType>ENTITY</persistenceType>
            <validateType></validateType>
            <validateRule></validateRule>
            <validateTip></validateTip>
            <validateErr>0</validateErr>
            <tooltip></tooltip>
            <copy>false</copy>
            <displayRule></displayRule>
            <calcFormula></calcFormula>
            <propsVal>{}</propsVal>
        </boItem>
        <boItem>
            <id>09ee8736-ff6b-4b67-96c6-172786f94888</id>
            <name>XXDJDW_GAJGMC</name>
            <title>信息登记单位_公安机关名称</title>
            <columnType>TEXT</columnType>
            <length>200</length>
            <nullable>true</nullable>
            <defaultValue></defaultValue>
            <columnWidth>150</columnWidth>
            <componentId>AWSUI.Text</componentId>
            <componentSetting>{"search":"0"}</componentSetting>
            <display>true</display>
            <deleted>false</deleted>
            <modify>true</modify>
            <componentExtendCode></componentExtendCode>
            <persistenceType>ENTITY</persistenceType>
            <validateType></validateType>
            <validateRule></validateRule>
            <validateTip></validateTip>
            <validateErr>0</validateErr>
            <tooltip></tooltip>
            <copy>false</copy>
            <displayRule></displayRule>
            <calcFormula></calcFormula>
            <propsVal>{}</propsVal>
        </boItem>
        <boItem>
            <id>a4200e8b-d48b-4938-9285-2d38907d5c1e</id>
            <name>XXDJRY_XM</name>
            <title>信息登记人员_姓名</title>
            <columnType>TEXT</columnType>
            <length>50</length>
            <nullable>true</nullable>
            <defaultValue></defaultValue>
            <columnWidth>100</columnWidth>
            <componentId>AWSUI.Text</componentId>
            <componentSetting>{"search":"0"}</componentSetting>
            <display>true</display>
            <deleted>false</deleted>
            <modify>true</modify>
            <componentExtendCode></componentExtendCode>
            <persistenceType>ENTITY</persistenceType>
            <validateType></validateType>
            <validateRule></validateRule>
            <validateTip></validateTip>
            <validateErr>0</validateErr>
            <tooltip></tooltip>
            <copy>false</copy>
            <displayRule></displayRule>
            <calcFormula></calcFormula>
            <propsVal>{}</propsVal>
        </boItem>
        <boItem>
            <id>83ef28ea-a890-401e-bbcc-ca647aba5cff</id>
            <name>XXDJRY_GMSFHM</name>
            <title>信息登记人员_公民身份号码</title>
            <columnType>TEXT</columnType>
            <length>18</length>
            <nullable>true</nullable>
            <defaultValue></defaultValue>
            <columnWidth>60</columnWidth>
            <componentId>AWSUI.Text</componentId>
            <componentSetting>{"search":"0"}</componentSetting>
            <display>true</display>
            <deleted>false</deleted>
            <modify>true</modify>
            <componentExtendCode></componentExtendCode>
            <persistenceType>ENTITY</persistenceType>
            <validateType></validateType>
            <validateRule></validateRule>
            <validateTip></validateTip>
            <validateErr>0</validateErr>
            <tooltip></tooltip>
            <copy>false</copy>
            <displayRule></displayRule>
            <calcFormula></calcFormula>
            <propsVal>{}</propsVal>
        </boItem>
        <boItem>
            <id>53e43eca-9ae4-4076-aef8-6602972430b4</id>
            <name>XXDJRY_LXDH</name>
            <title>信息登记人员_联系电话</title>
            <columnType>TEXT</columnType>
            <length>20</length>
            <nullable>true</nullable>
            <defaultValue></defaultValue>
            <columnWidth>60</columnWidth>
            <componentId>AWSUI.Text</componentId>
            <componentSetting>{"search":"0"}</componentSetting>
            <display>true</display>
            <deleted>false</deleted>
            <modify>true</modify>
            <componentExtendCode></componentExtendCode>
            <persistenceType>ENTITY</persistenceType>
            <validateType></validateType>
            <validateRule></validateRule>
            <validateTip></validateTip>
            <validateErr>0</validateErr>
            <tooltip></tooltip>
            <copy>false</copy>
            <displayRule></displayRule>
            <calcFormula></calcFormula>
            <propsVal>{}</propsVal>
        </boItem>
        <boItem>
            <id>a990a193-053e-4158-a1a8-23006c45ec9b</id>
            <name>XXSC_PDBZ</name>
            <title>信息删除_判断标识/CODE_IF</title>
            <columnType>TEXT</columnType>
            <length>1</length>
            <nullable>true</nullable>
            <defaultValue>0</defaultValue>
            <columnWidth>60</columnWidth>
            <componentId>AWSUI.Text</componentId>
            <componentSetting>{"search":"0"}</componentSetting>
            <display>true</display>
            <deleted>false</deleted>
            <modify>true</modify>
            <componentExtendCode></componentExtendCode>
            <persistenceType>ENTITY</persistenceType>
            <validateType></validateType>
            <validateRule></validateRule>
            <validateTip></validateTip>
            <validateErr>0</validateErr>
            <tooltip></tooltip>
            <copy>false</copy>
            <displayRule></displayRule>
            <calcFormula></calcFormula>
            <propsVal>{}</propsVal>
        </boItem>
    </boItems>
    <boIndexs/>
    <boRelations/>
</boModel>
